stprofiler/__init__.py
stprofiler/classify/__init__.py
stprofiler/classify/KNN_classify.py
stprofiler/classify/MLP_classify.py
stprofiler/classify/result_plot.py
stprofiler/classify/RF_classify.py
stprofiler/feature/__init__.py
stprofiler/feature/feature_extraction.py
"stprofiler/image/__init__,py"
stprofiler/image/cell_classify.py
stprofiler/image/cell_segmentation.py
stprofiler/image/foci_detection.py
stprofiler-0.0.5.dist-info/LICENSE
stprofiler-0.0.5.dist-info/METADATA
stprofiler-0.0.5.dist-info/WHEEL
stprofiler-0.0.5.dist-info/RECORD
