Metadata-Version: 2.1
Name: stprofiler
Version: 0.0.5
Summary: a package for analyzing spatial transcriptomic features of smFISH images
License: MIT
Author: Garrick Chang
Author-email: changg@iu.edu
Requires-Python: >=3.8,<3.9
Classifier: License :: OSI Approved :: MIT License
Classifier: Programming Language :: Python :: 3
Classifier: Programming Language :: Python :: 3.8
Requires-Dist: imbalanced-learn (==0.12.3)
Requires-Dist: matplotlib (==3.7.5)
Requires-Dist: numpy (==1.24.4)
Requires-Dist: pandas (==2.0.3)
Requires-Dist: pillow (==10.3.0)
Requires-Dist: scikit-image (==0.21.0)
Requires-Dist: scikit-learn (==1.3.2)
Requires-Dist: scipy (==1.10.1)
Requires-Dist: seaborn (==0.13.2)
Requires-Dist: segment-anything (==1.0)
Requires-Dist: tqdm (==4.66.4)
